[
  {
    "name": "Voyager 1",
    "id": "-31",
    "distanceKm": 25400390742.177742,
    "velocityKmS": -5.5411217,
    "missionType": "Interstellar Probe",
    "ra": 259.2445,
    "dec": 12.273027777777779,
    "date": "2026-04-01T18:47:17.246Z",
    "status": "AWAITING SIGNAL"
  },
  {
    "name": "Voyager 2",
    "id": "-32",
    "distanceKm": 21336342559.453644,
    "velocityKmS": -7.873838,
    "missionType": "Interstellar Probe",
    "ra": 303.76141666666666,
    "dec": -59.334805555555555,
    "date": "2026-04-01T18:47:17.974Z",
    "status": "AWAITING SIGNAL"
  },
  {
    "name": "New Horizons",
    "id": "-98",
    "distanceKm": 9636457266.653399,
    "velocityKmS": -15.817531,
    "missionType": "Pluto/Kuiper Belt",
    "ra": 290.57912500000003,
    "dec": -20.080444444444446,
    "date": "2026-04-01T18:47:18.705Z",
    "status": "AWAITING SIGNAL"
  },
  {
    "name": "James Webb",
    "id": "-170",
    "distanceKm": 1302910.6109854123,
    "velocityKmS": 0.1218086,
    "missionType": "Space Telescope",
    "ra": 213.30729166666666,
    "dec": -3.0438888888888886,
    "date": "2026-04-01T18:47:19.429Z",
    "status": "AWAITING SIGNAL"
  },
  {
    "name": "Parker Solar Probe",
    "id": "-96",
    "distanceKm": 206147823.30768317,
    "velocityKmS": 17.0425849,
    "missionType": "Heliophysics",
    "ra": 350.62470833333333,
    "dec": -5.2901388888888885,
    "date": "2026-04-01T18:47:20.151Z",
    "status": "AWAITING SIGNAL"
  }
]