[
  {
    "name": "Voyager 1",
    "id": "-31",
    "distanceKm": 25439728279.6433,
    "velocityKmS": 20.4243127,
    "missionType": "Interstellar Probe",
    "ra": 258.9062083333333,
    "dec": 12.422055555555556,
    "date": "2026-06-17T01:34:48.800Z",
    "status": "AWAITING SIGNAL"
  },
  {
    "name": "Voyager 2",
    "id": "-32",
    "distanceKm": 21308622787.96488,
    "velocityKmS": 5.1187069,
    "missionType": "Interstellar Probe",
    "ra": 303.5427916666667,
    "dec": -59.69869444444444,
    "date": "2026-06-17T01:34:49.519Z",
    "status": "AWAITING SIGNAL"
  },
  {
    "name": "New Horizons",
    "id": "-98",
    "distanceKm": 9566338683.384634,
    "velocityKmS": 1.8161866,
    "missionType": "Pluto/Kuiper Belt",
    "ra": 290.0647083333333,
    "dec": -20.113333333333333,
    "date": "2026-06-17T01:34:50.255Z",
    "status": "AWAITING SIGNAL"
  },
  {
    "name": "James Webb",
    "id": "-170",
    "distanceKm": 1746248.510569001,
    "velocityKmS": 0.0063481,
    "missionType": "Space Telescope",
    "ra": 262.0329583333333,
    "dec": -35.436388888888885,
    "date": "2026-06-17T01:34:50.984Z",
    "status": "AWAITING SIGNAL"
  },
  {
    "name": "Parker Solar Probe",
    "id": "-96",
    "distanceKm": 107874423.89765768,
    "velocityKmS": -22.4142053,
    "missionType": "Heliophysics",
    "ra": 69.489875,
    "dec": 21.00725,
    "date": "2026-06-17T01:34:51.715Z",
    "status": "AWAITING SIGNAL"
  }
]