[
  {
    "name": "Voyager 1",
    "id": "-31",
    "distanceKm": 25434992149.270706,
    "velocityKmS": -0.4351332,
    "missionType": "Interstellar Probe",
    "ra": 259.13354166666664,
    "dec": 12.06563888888889,
    "date": "2026-01-22T18:44:45.034Z",
    "status": "AWAITING SIGNAL"
  },
  {
    "name": "Voyager 2",
    "id": "-32",
    "distanceKm": 21339831301.287872,
    "velocityKmS": 10.672192,
    "missionType": "Interstellar Probe",
    "ra": 303.0084583333333,
    "dec": -59.19852777777778,
    "date": "2026-01-22T18:44:45.712Z",
    "status": "AWAITING SIGNAL"
  },
  {
    "name": "New Horizons",
    "id": "-98",
    "distanceKm": 9678304230.354992,
    "velocityKmS": 6.8898335,
    "missionType": "Pluto/Kuiper Belt",
    "ra": 289.82254166666667,
    "dec": -20.205194444444444,
    "date": "2026-01-22T18:44:46.404Z",
    "status": "AWAITING SIGNAL"
  },
  {
    "name": "James Webb",
    "id": "-170",
    "distanceKm": 1622137.551128254,
    "velocityKmS": -0.0554869,
    "missionType": "Space Telescope",
    "ra": 94.21883333333332,
    "dec": 16.483249999999998,
    "date": "2026-01-22T18:44:47.095Z",
    "status": "AWAITING SIGNAL"
  },
  {
    "name": "Parker Solar Probe",
    "id": "-96",
    "distanceKm": 251584532.1231439,
    "velocityKmS": 6.0476046,
    "missionType": "Heliophysics",
    "ra": 313.328625,
    "dec": -18.89397222222222,
    "date": "2026-01-22T18:44:47.777Z",
    "status": "AWAITING SIGNAL"
  }
]