[
  {
    "name": "Voyager 1",
    "id": "-31",
    "distanceKm": 25394652542.961636,
    "velocityKmS": 1.5336375,
    "missionType": "Interstellar Probe",
    "ra": 259.15954166666666,
    "dec": 12.355833333333333,
    "date": "2026-04-29T01:13:59.173Z",
    "dsnSignal": {
      "id": "-31",
      "name": "VGR1",
      "upSignal": false,
      "downSignal": true,
      "dataRate": 160,
      "power": -160,
      "frequency": 0
    },
    "status": "DOWNLINK ACTIVE"
  },
  {
    "name": "Voyager 2",
    "id": "-32",
    "distanceKm": 21317065894.364674,
    "velocityKmS": -7.1620868,
    "missionType": "Interstellar Probe",
    "ra": 303.8270416666667,
    "dec": -59.465694444444445,
    "date": "2026-04-29T01:13:59.900Z",
    "status": "AWAITING SIGNAL"
  },
  {
    "name": "New Horizons",
    "id": "-98",
    "distanceKm": 9598394685.57543,
    "velocityKmS": -14.5042489,
    "missionType": "Pluto/Kuiper Belt",
    "ra": 290.5557916666667,
    "dec": -20.06838888888889,
    "date": "2026-04-29T01:14:00.629Z",
    "status": "AWAITING SIGNAL"
  },
  {
    "name": "James Webb",
    "id": "-170",
    "distanceKm": 1596054.5937008352,
    "velocityKmS": 0.1072557,
    "missionType": "Space Telescope",
    "ra": 246.35375,
    "dec": -23.857000000000003,
    "date": "2026-04-29T01:14:01.360Z",
    "dsnSignal": {
      "id": "-170",
      "name": "JWST",
      "upSignal": false,
      "downSignal": true,
      "dataRate": 40000,
      "power": -120,
      "frequency": 0
    },
    "status": "DOWNLINK ACTIVE"
  },
  {
    "name": "Parker Solar Probe",
    "id": "-96",
    "distanceKm": 212458434.27391663,
    "velocityKmS": -8.3780698,
    "missionType": "Heliophysics",
    "ra": 9.293166666666666,
    "dec": 2.2208333333333337,
    "date": "2026-04-29T01:14:02.093Z",
    "status": "AWAITING SIGNAL"
  }
]