[
  {
    "name": "Voyager 1",
    "id": "-31",
    "distanceKm": 25459095914.916496,
    "velocityKmS": 24.3761884,
    "missionType": "Interstellar Probe",
    "ra": 258.85125,
    "dec": 12.419611111111111,
    "date": "2026-06-27T01:21:04.701Z",
    "status": "AWAITING SIGNAL"
  },
  {
    "name": "Voyager 2",
    "id": "-32",
    "distanceKm": 21314612724.231045,
    "velocityKmS": 8.7776356,
    "missionType": "Interstellar Probe",
    "ra": 303.43608333333333,
    "dec": -59.736111111111114,
    "date": "2026-06-27T01:21:05.416Z",
    "dsnSignal": {
      "id": "-32",
      "name": "VGR2",
      "upSignal": false,
      "downSignal": true,
      "dataRate": 160,
      "power": -160,
      "frequency": 0
    },
    "status": "DOWNLINK ACTIVE"
  },
  {
    "name": "New Horizons",
    "id": "-98",
    "distanceKm": 9569952472.615568,
    "velocityKmS": 6.5848926,
    "missionType": "Pluto/Kuiper Belt",
    "ra": 289.918625,
    "dec": -20.130388888888888,
    "date": "2026-06-27T01:21:06.149Z",
    "dsnSignal": {
      "id": "-98",
      "name": "NHPC",
      "upSignal": false,
      "downSignal": true,
      "dataRate": 50,
      "power": -150,
      "frequency": 0
    },
    "status": "DOWNLINK ACTIVE"
  },
  {
    "name": "James Webb",
    "id": "-170",
    "distanceKm": 1750979.433460955,
    "velocityKmS": -0.0051711,
    "missionType": "Space Telescope",
    "ra": 263.2125833333333,
    "dec": -34.874361111111114,
    "date": "2026-06-27T01:21:06.874Z",
    "dsnSignal": {
      "id": "-170",
      "name": "JWST",
      "upSignal": false,
      "downSignal": true,
      "dataRate": 28000000,
      "power": -93,
      "frequency": 0
    },
    "status": "DOWNLINK ACTIVE"
  },
  {
    "name": "Parker Solar Probe",
    "id": "-96",
    "distanceKm": 94604364.92884472,
    "velocityKmS": -11.7295401,
    "missionType": "Heliophysics",
    "ra": 64.08779166666667,
    "dec": 18.882583333333333,
    "date": "2026-06-27T01:21:07.590Z",
    "status": "AWAITING SIGNAL"
  }
]